pixiv_tag_downloader/__init__.py
pixiv_tag_downloader/__main__.py
pixiv_tag_downloader/api/__init__.py
pixiv_tag_downloader/api/pixiv.py
pixiv_tag_downloader/auth/__init__.py
pixiv_tag_downloader/auth/cookie.py
pixiv_tag_downloader/config/__init__.py
pixiv_tag_downloader/config/config_manager.py
pixiv_tag_downloader/download/__init__.py
pixiv_tag_downloader/download/aria2.py
pixiv_tag_downloader/download/direct.py
pixiv_tag_downloader/i18n/__init__.py
pixiv_tag_downloader/i18n/translation.py
pixiv_tag_downloader/ui/__init__.py
pixiv_tag_downloader/ui/cli.py
pixiv_tag_downloader/utils/__init__.py
pixiv_tag_downloader/utils/file_utils.py
pixiv_tag_downloader/utils/path_formatter.py
pixiv_tag_downloader-1.0.2.dist-info/METADATA
pixiv_tag_downloader-1.0.2.dist-info/WHEEL
pixiv_tag_downloader-1.0.2.dist-info/entry_points.txt
pixiv_tag_downloader-1.0.2.dist-info/top_level.txt
pixiv_tag_downloader-1.0.2.dist-info/RECORD
