Metadata-Version: 2.1
Name: pixiv-tag-downloader
Version: 1.0.2
Summary: 根据标签下载Pixiv用户作品的工具
Home-page: https://github.com/TrustAsia/PixivTagDownloader
Author: Mannix Sun
Author-email: Mannix Sun <root@teamcs.org>
License: MIT
Project-URL: Homepage, https://github.com/example/pixiv_tag_downloader
Project-URL: Issues, https://github.com/example/pixiv_tag_downloader/issues
Project-URL: Documentation, https://github.com/example/pixiv_tag_downloader#readme
Project-URL: Source, https://github.com/example/pixiv_tag_downloader
Keywords: pixiv,download,tag,artwork,manga,novel
Classifier: Development Status :: 5 - Production/Stable
Classifier: Intended Audience :: End Users/Desktop
Classifier: License :: OSI Approved :: MIT License
Classifier: Programming Language :: Python :: 3
Classifier: Programming Language :: Python :: 3.8
Classifier: Programming Language :: Python :: 3.9
Classifier: Programming Language :: Python :: 3.10
Classifier: Programming Language :: Python :: 3.11
Classifier: Topic :: Internet :: WWW/HTTP :: Indexing/Search
Classifier: Topic :: Multimedia :: Graphics
Classifier: Topic :: Utilities
Requires-Python: >=3.8
Requires-Dist: requests >=2.28.0
Requires-Dist: beautifulsoup4 >=4.11.0
Requires-Dist: pyyaml >=6.0
Requires-Dist: tqdm >=4.64.0
Requires-Dist: jsonschema >=4.16.0
Requires-Dist: xmlrpc-aria2 >=1.0.2
Requires-Dist: colorama >=0.4.6
Requires-Dist: python-dateutil >=2.8.2
